Metadata-Version: 2.1
Name: naps-track
Version: 1.0.7
Summary: NAPS (NAPS is ArUco Plus SLEAP)
Home-page: https://github.com/kocherlab/naps
License: MIT
Project-URL: Documentation, https://naps.readthedocs.io/en/latest/
Project-URL: Code, https://github.com/kocherlab/naps
Project-URL: Issue tracker, https://github.com/kocherlab/naps/issues
Platform: UNKNOWN
Requires-Python: >=3.7
